{
  "UUID": "799b8652-4ce9-4465-a271-3e75aa3bf4a2",
  "class": "com.runrev.engine.group",
  "customPropertySets": {
    "cREVGeneral": {
      "revUniqueID": "1432730204692"
    }
  },
  "properties": {
    "altId": "0",
    "backColor": "",
    "backPattern": "",
    "backgroundBehavior": "false",
    "behavior": "",
    "blendLevel": "0",
    "borderColor": "",
    "borderPattern": "",
    "borderWidth": "2",
    "bottomColor": "",
    "bottomPattern": "",
    "boundingRect": "",
    "cantDelete": "false",
    "cantSelect": "false",
    "colorOverlay": "",
    "disabled": "false",
    "dontSearch": "false",
    "dropShadow": "",
    "focusColor": "",
    "focusPattern": "",
    "foreColor": "",
    "forePattern": "",
    "hScroll": "0",
    "hScrollbar": "false",
    "hiliteColor": "",
    "hilitePattern": "",
    "hilitedButton": "0",
    "id": "1730",
    "ink": "srcCopy",
    "innerGlow": "",
    "innerShadow": "",
    "label": "",
    "layerMode": "static",
    "lockLoc": "false",
    "margins": "2",
    "name": "RightAndLeft",
    "opaque": "false",
    "outerGlow": "",
    "radioBehavior": "true",
    "scrollbarWidth": "20",
    "selectGroupedControls": "true",
    "shadowColor": "",
    "shadowOffset": "4",
    "shadowPattern": "",
    "sharedBehavior": "false",
    "showBorder": "false",
    "showFocusBorder": "true",
    "showName": "false",
    "tabGroupBehavior": "false",
    "textFont": "",
    "textSize": "",
    "textStyle": "",
    "threeD": "true",
    "toolTip": "",
    "topColor": "",
    "topPattern": "",
    "traversalOn": "true",
    "unboundedHScroll": "false",
    "unboundedVScroll": "false",
    "vScroll": "0",
    "vScrollbar": "false",
    "visible": "false"
  }
}